README.rst
activesoup/__init__.py
activesoup/driver.py
activesoup/html.py
activesoup/response.py
activesoup-0.3.2.dist-info/LICENSE
activesoup-0.3.2.dist-info/WHEEL
activesoup-0.3.2.dist-info/METADATA
activesoup-0.3.2.dist-info/RECORD
