Metadata-Version: 2.1
Name: activesoup
Version: 0.3.2
Summary: A pure-python headless browser
Home-page: https://activesoup.dev
License: MIT
Author: James Elford
Author-email: james.p.elford@gmail.com
Requires-Python: >=3.6.7,<4.0.0
Classifier: Development Status :: 3 - Alpha
Classifier: License :: OSI Approved :: MIT License
Classifier: Programming Language :: Python :: 3
Classifier: Programming Language :: Python :: 3.10
Classifier: Programming Language :: Python :: 3.7
Classifier: Programming Language :: Python :: 3.8
Classifier: Programming Language :: Python :: 3.9
Requires-Dist: html5lib (>=0.9)
Requires-Dist: requests (>=2.9.0,<3.0.0)
Requires-Dist: typing_extensions (>=3.10,<4.0)
Project-URL: Repository, https://github.com/jelford/activesoup
